asvprotobuf/__init__.py
asvprotobuf/nav_pb2.py
asvprotobuf/sensor_pb2.py
asvprotobuf/std_pb2.py
asvprotobuf-0.4.0.dist-info/METADATA
asvprotobuf-0.4.0.dist-info/WHEEL
asvprotobuf-0.4.0.dist-info/top_level.txt
asvprotobuf-0.4.0.dist-info/zip-safe
asvprotobuf-0.4.0.dist-info/RECORD
