Metadata-Version: 2.1
Name: asvprotobuf
Version: 0.4.0
Summary: ASV API for using protobuf for serialization and deserialization of objects
Home-page: https://github.com/akashp1997/asv_protobuf
Author: Akash Purandare
Author-email: akash.purandare@srmasv.in
License: BSD-3-Clause
Keywords: asvprotobuf
Platform: UNKNOWN
Requires-Dist: protobuf (==3.6.1)
